exdpy/__init__.py
exdpy/client.py
exdpy/common.py
exdpy/constants.py
exdpy/http.py
exdpy/raw.py
exdpy/replay.py
exchangedataset_python-1.1.0.dist-info/LICENSE
exchangedataset_python-1.1.0.dist-info/METADATA
exchangedataset_python-1.1.0.dist-info/WHEEL
exchangedataset_python-1.1.0.dist-info/top_level.txt
exchangedataset_python-1.1.0.dist-info/RECORD
