Metadata-Version: 2.1
Name: exchangedataset-python
Version: 1.1.0
Summary: Python version of Exchangedataset historical cryptocurrency market data streaming service.
Home-page: https://github.com/exchangedataset/exchangedataset-python
Author: Exchangedataset
Author-email: support@exchangedataset.cc
License: MIT
Platform: UNKNOWN
Classifier: License :: OSI Approved :: MIT License
Classifier: Programming Language :: Python
Classifier: Programming Language :: Python :: 3
Classifier: Programming Language :: Python :: 3.8
Classifier: Programming Language :: Python :: Implementation :: CPython
Classifier: Programming Language :: Python :: Implementation :: PyPy
Requires-Python: >=3.8.0
Requires-Dist: requests
